mousetumortrack/__init__.py
mousetumortrack/_version.py
mousetumortrack/register.py
mousetumortrack/track.py
mousetumortrack-0.0.3.dist-info/LICENSE
mousetumortrack-0.0.3.dist-info/METADATA
mousetumortrack-0.0.3.dist-info/WHEEL
mousetumortrack-0.0.3.dist-info/top_level.txt
mousetumortrack-0.0.3.dist-info/RECORD
