Metadata-Version: 2.1
Name: mousetumortrack
Version: 0.0.3
Summary: Tracking tumor nodules in mice CT scans.
Author-email: Mallory Wittwer <mallory.wittwer@epfl.ch>
License:                     GNU AFFERO GENERAL PUBLIC LICENSE
Project-URL: homepage, https://github.com/EPFL-Center-for-Imaging/mousetumortrack
Project-URL: repository, https://github.com/EPFL-Center-for-Imaging/mousetumortrack
Classifier: Development Status :: 2 - Pre-Alpha
Classifier: License :: OSI Approved :: BSD License
Classifier: Programming Language :: Python :: 3
Classifier: Programming Language :: Python :: 3.9
Classifier: Programming Language :: Python :: 3.10
Classifier: Topic :: Scientific/Engineering :: Image Processing
Requires-Python: >=3.9
License-File: LICENSE
Requires-Dist: numpy
Requires-Dist: pandas
Requires-Dist: scikit-image
Requires-Dist: trackpy
Requires-Dist: laptrack
Requires-Dist: vedo
Requires-Dist: mouselungseg
